mqt/ionshuttler/__init__.py
mqt/ionshuttler/multi_shuttler/__init__.py
mqt/ionshuttler/multi_shuttler/__main__.py
mqt/ionshuttler/multi_shuttler/inside/__init__.py
mqt/ionshuttler/multi_shuttler/inside/compilation.py
mqt/ionshuttler/multi_shuttler/inside/cycles.py
mqt/ionshuttler/multi_shuttler/inside/graph.py
mqt/ionshuttler/multi_shuttler/inside/graph_creator.py
mqt/ionshuttler/multi_shuttler/inside/graph_utils.py
mqt/ionshuttler/multi_shuttler/inside/partition.py
mqt/ionshuttler/multi_shuttler/inside/paths.py
mqt/ionshuttler/multi_shuttler/inside/plotting.py
mqt/ionshuttler/multi_shuttler/inside/processing_zone.py
mqt/ionshuttler/multi_shuttler/inside/scheduling.py
mqt/ionshuttler/multi_shuttler/inside/shuttle.py
mqt/ionshuttler/multi_shuttler/inside/types.py
mqt/ionshuttler/multi_shuttler/main.py
mqt/ionshuttler/multi_shuttler/outside/__init__.py
mqt/ionshuttler/multi_shuttler/outside/compilation.py
mqt/ionshuttler/multi_shuttler/outside/cycles.py
mqt/ionshuttler/multi_shuttler/outside/graph.py
mqt/ionshuttler/multi_shuttler/outside/graph_creator.py
mqt/ionshuttler/multi_shuttler/outside/graph_utils.py
mqt/ionshuttler/multi_shuttler/outside/partition.py
mqt/ionshuttler/multi_shuttler/outside/paths.py
mqt/ionshuttler/multi_shuttler/outside/plotting.py
mqt/ionshuttler/multi_shuttler/outside/processing_zone.py
mqt/ionshuttler/multi_shuttler/outside/scheduling.py
mqt/ionshuttler/multi_shuttler/outside/shuttle.py
mqt/ionshuttler/multi_shuttler/outside/types.py
mqt/ionshuttler/py.typed
mqt/ionshuttler/single_shuttler/__init__.py
mqt/ionshuttler/single_shuttler/__main__.py
mqt/ionshuttler/single_shuttler/compilation.py
mqt/ionshuttler/single_shuttler/cycles.py
mqt/ionshuttler/single_shuttler/graph_utils.py
mqt/ionshuttler/single_shuttler/main.py
mqt/ionshuttler/single_shuttler/memory_sat.py
mqt/ionshuttler/single_shuttler/plotting.py
mqt/ionshuttler/single_shuttler/run_benchmarks.py
mqt/ionshuttler/single_shuttler/run_heuristic.py
mqt_ionshuttler-0.2.4.dist-info/licenses/LICENSE.md
mqt_ionshuttler-0.2.4.dist-info/WHEEL
mqt_ionshuttler-0.2.4.dist-info/entry_points.txt
mqt_ionshuttler-0.2.4.dist-info/METADATA
mqt_ionshuttler-0.2.4.dist-info/RECORD
