Metadata-Version: 2.4
Name: mqt-ionshuttler
Version: 0.2.4
Summary: A solver for the shuttling problem in QCCD quantum computers
Keywords: MQT,quantum computing,compilation,shuttling,design automation,SAT solver
Author: Daniel Schoenberger
Author-email: Daniel Schoenberger <daniel.schoenberger@tum.de>
License-Expression: MIT
License-File: LICENSE.md
Classifier: Development Status :: 4 - Beta
Classifier: Intended Audience :: Science/Research
Classifier: Natural Language :: English
Classifier: Operating System :: POSIX :: Linux
Classifier: Operating System :: MacOS
Classifier: Operating System :: Microsoft :: Windows
Classifier: Programming Language :: Python
Classifier: Programming Language :: Python :: 3
Classifier: Programming Language :: Python :: 3 :: Only
Classifier: Programming Language :: Python :: 3.10
Classifier: Programming Language :: Python :: 3.11
Classifier: Programming Language :: Python :: 3.12
Classifier: Programming Language :: Python :: 3.13
Classifier: Programming Language :: Python :: 3.14
Classifier: Topic :: Scientific/Engineering :: Electronic Design Automation (EDA)
Classifier: Typing :: Typed
Requires-Dist: qiskit>=1.0.0
Requires-Dist: numpy>=1.26
Requires-Dist: numpy>=2.1 ; python_full_version >= '3.13'
Requires-Dist: numpy>=2.3.2 ; python_full_version >= '3.14'
Requires-Dist: z3-solver>=4.15.3
Requires-Dist: matplotlib>=3.7.1
Requires-Dist: matplotlib>=3.8 ; python_full_version >= '3.12'
Requires-Dist: matplotlib>=3.10 ; python_full_version >= '3.13'
Requires-Dist: matplotlib>=3.10.5 ; python_full_version >= '3.14'
Requires-Dist: networkx>=3.0
Requires-Dist: more-itertools>=10.1.0
Requires-Python: >=3.10
Project-URL: Discussions, https://github.com/munich-quantum-toolkit/ionshuttler/discussions
Project-URL: Documentation, https://mqt.readthedocs.io/projects/ionshuttler
Project-URL: Homepage, https://github.com/munich-quantum-toolkit/ionshuttler
Project-URL: Issues, https://github.com/munich-quantum-toolkit/ionshuttler/issues
